{
    "id": 4396,
    "telegram_link": "https://t.me/vkusnypiter/4396",
    "text_html": "Греческая таверна <strong>Pame</strong> — это любовь с первого взгляда <a href=\"stickers/sticker (1).webp\">💫</a><br/><br/>Ресторан находится в здании Круглого рынка, в паре минут от Марсового поля. Первый этаж Pame выделен под ресторан, а этажом ниже царит более неформальная атмосфера: для распития коктейлей и танцев.<br/><br/>В меню упор на греческую кухню с возможными отклонениями от канонов. Таких, как оливье с осьминогом в гранатовом демиглясе. Порцию этого блюда по умолчанию делают на двоих <a href=\"stickers/sticker (39).webp\">🍽</a><br/><br/>Начинать знакомство с кухней стоит с дипа из тунца с хрустящими каперсами. Его много, поэтому сразу заказывайте дополнительную лепёшку. Их команда привозит из Греции и уже на месте доводит до ума: дожаривают и приправляют специями.<br/><br/>Среди горячих блюд фаворита выделить сложно. За титул сражаются и орзо с морепродуктами, и форель с луком-порей и грецким орехом, и клефтико из томлёной говядины <a href=\"stickers/sticker (22).webp\">🍽</a><br/><br/>Все блюда, о которых я написал в этом посте, кратно повысили мою любовь к греческой кухне. А Pame и вовсе сохранил в списке избранных мест.<br/><br/><a href=\"stickers/sticker (3).webp\">〰️</a> <a href=\"https://go.2gis.com/fox75w\">Наб. реки Мойки, 3а</a><br/><a href=\"stickers/sticker (3).webp\">〰️</a> <a href=\"https://www.instagram.com/pametaverna/\">Ссылка на IG</a><br/><br/><a href=\"\" onclick='return ShowHashtag(\"Невский_проспект\")'>#Невский_проспект</a> <a href=\"\" onclick='return ShowHashtag(\"Адмиралтейская\")'>#Адмиралтейская</a> <a href=\"\" onclick='return ShowHashtag(\"средиземноморская_кухня\")'>#средиземноморская_кухня</a><br/><br/><a href=\"stickers/sticker (4).webp\">✌️</a> Нравится пост? <a href=\"https://t.me/vkusnypiter?boost\">Бусти канал.</a>",
    "hashtags": [
        "#адмиралтейская",
        "#невский_проспект",
        "#средиземноморская_кухня"
    ],
    "photos_count": 5
}