{
    "id": 4239,
    "telegram_link": "https://t.me/vkusnypiter/4239",
    "text_html": "Сегодня завтракаем в <strong>Bist</strong> — мясном ресторане итальянской кухни <a href=\"stickers/sticker (62).webp\">🍳</a><br/><br/>Обзор на сам ресторан и основное меню я уже <a href=\"https://t.me/vkusnypiter/2665\">делал</a>, а вот до завтраков добрался только сейчас.<br/><br/>Наиболее сытным вариантом будет большой мясной итальянский завтрак. Омлет, сочный стейк мачете, печёный картофель и овощи с соусом на основе зелени <a href=\"stickers/sticker (10).webp\">🍽</a><br/><br/>Если не захотите ограничиваться одним блюдом, берите шикарный крок-мадам с тамбовским окороком и овсяную кашу с ягодами — от обоих блюд мы с Дашей в восторгах.<br/><br/>На десерт присмотритесь к увесистому пончику с названием, которое переводится как \"к чёрту диету\". Вариант не для ЗОЖников <a href=\"stickers/sticker (13).webp\">☀️</a><br/><br/>Попробовать всю эту красоту можно до часа дня по будням и до 3 часов дня по выходным.<br/><br/><a href=\"stickers/sticker (3).webp\">〰️</a> +7 931 994-75-15<br/><a href=\"stickers/sticker (3).webp\">〰️</a> <a href=\"https://go.2gis.com/gfeh8\">Большой пр. В.О., 18<br/></a><a href=\"stickers/sticker (3).webp\">〰️</a> <a href=\"https://italyco.rest/Bist\">Ссылка на сайт</a><br/><br/><a href=\"\" onclick='return ShowHashtag(\"Василеостровская\")'>#Василеостровская</a> <a href=\"\" onclick='return ShowHashtag(\"Спортивная\")'>#Спортивная</a> <a href=\"\" onclick='return ShowHashtag(\"завтраки\")'>#завтраки</a><br/><br/>Где и чем ещё можно позавтракать:<br/>→ <a href=\"https://t.me/vkusnypiter/3956\">Картофельным драником в Paloma Cantina</a>.<br/>→ <a href=\"https://t.me/vkusnypiter/3315\">Кацу сэндвичем с курицей в Kuta x Chang</a>.<br/>→ <a href=\"https://t.me/vkusnypiter/4159\">Черёмуховыми оладьями с черникой в Amelie</a>.<a href=\"https://www.instagram.com/bist.bar/\"><br/></a><br/><a href=\"stickers/sticker (4).webp\">✌️</a> Нравится пост? <a href=\"https://t.me/vkusnypiter?boost\">Бусти канал</a>.",
    "hashtags": [
        "#василеостровская",
        "#завтраки",
        "#спортивная"
    ],
    "photos_count": 5
}